{".class":"MypyFile","_fullname":"prefect.utilities.dispatch","future_import_flags":[],"is_partial_stub_package":false,"is_stub":false,"names":{".class":"SymbolTable","Any":{".class":"SymbolTableNode","cross_ref":"typing.Any","kind":"Gdef"},"Dict":{".class":"SymbolTableNode","cross_ref":"typing.Dict","kind":"Gdef"},"Optional":{".class":"SymbolTableNode","cross_ref":"typing.Optional","kind":"Gdef"},"T":{".class":"SymbolTableNode","kind":"Gdef","node":{".class":"TypeVarExpr","default":{".class":"AnyType","missing_import_name":null,"source_any":null,"type_of_any":4},"fullname":"prefect.utilities.dispatch.T","name":"T","upper_bound":{".class":"TypeType","item":{".class":"AnyType","missing_import_name":null,"source_any":null,"type_of_any":4}},"values":[],"variance":0}},"Type":{".class":"SymbolTableNode","cross_ref":"typing.Type","kind":"Gdef"},"TypeVar":{".class":"SymbolTableNode","cross_ref":"typing.TypeVar","kind":"Gdef"},"_TYPE_REGISTRIES":{".class":"SymbolTableNode","kind":"Gdef","node":{".class":"Var","flags":["is_ready","has_explicit_value"],"fullname":"prefect.utilities.dispatch._TYPE_REGISTRIES","name":"_TYPE_REGISTRIES","type":{".class":"Instance","args":[{".class":"TypeType","item":{".class":"AnyType","missing_import_name":null,"source_any":null,"type_of_any":4}},{".class":"Instance","args":["builtins.str",{".class":"TypeType","item":{".class":"AnyType","missing_import_name":null,"source_any":null,"type_of_any":4}}],"extra_attrs":null,"type_ref":"builtins.dict"}],"extra_attrs":null,"type_ref":"builtins.dict"}}},"__annotations__":{".class":"SymbolTableNode","kind":"Gdef","node":{".class":"Var","flags":["is_ready"],"fullname":"prefect.utilities.dispatch.__annotations__","name":"__annotations__","type":{".class":"Instance","args":["builtins.str",{".class":"AnyType","missing_import_name":null,"source_any":null,"type_of_any":6}],"extra_attrs":null,"type_ref":"builtins.dict"}}},"__doc__":{".class":"SymbolTableNode","kind":"Gdef","node":{".class":"Var","flags":["is_ready"],"fullname":"prefect.utilities.dispatch.__doc__","name":"__doc__","type":"builtins.str"}},"__file__":{".class":"SymbolTableNode","kind":"Gdef","node":{".class":"Var","flags":["is_ready"],"fullname":"prefect.utilities.dispatch.__file__","name":"__file__","type":"builtins.str"}},"__name__":{".class":"SymbolTableNode","kind":"Gdef","node":{".class":"Var","flags":["is_ready"],"fullname":"prefect.utilities.dispatch.__name__","name":"__name__","type":"builtins.str"}},"__package__":{".class":"SymbolTableNode","kind":"Gdef","node":{".class":"Var","flags":["is_ready"],"fullname":"prefect.utilities.dispatch.__package__","name":"__package__","type":"builtins.str"}},"__spec__":{".class":"SymbolTableNode","kind":"Gdef","node":{".class":"Var","flags":["is_ready"],"fullname":"prefect.utilities.dispatch.__spec__","name":"__spec__","type":"_frozen_importlib.ModuleSpec"}},"_register_subclass_of_base_type":{".class":"SymbolTableNode","kind":"Gdef","node":{".class":"Decorator","func":{".class":"FuncDef","abstract_status":0,"arg_kinds":[0,4],"arg_names":["cls","kwargs"],"dataclass_transform_spec":null,"deprecated":null,"flags":["is_class","is_decorated"],"fullname":"prefect.utilities.dispatch._register_subclass_of_base_type","name":"_register_subclass_of_base_type","type":null},"is_overload":false,"var":{".class":"Var","flags":["is_classmethod","is_ready","is_inferred"],"fullname":"prefect.utilities.dispatch._register_subclass_of_base_type","name":"_register_subclass_of_base_type","type":{".class":"CallableType","arg_kinds":[0,4],"arg_names":["cls","kwargs"],"arg_types":[{".class":"AnyType","missing_import_name":null,"source_any":null,"type_of_any":1},{".class":"AnyType","missing_import_name":null,"source_any":null,"type_of_any":1}],"bound_args":[],"def_extras":{"first_arg":null},"fallback":"builtins.function","from_concatenate":false,"implicit":true,"imprecise_arg_kinds":false,"is_ellipsis_args":false,"name":"_register_subclass_of_base_type","ret_type":{".class":"AnyType","missing_import_name":null,"source_any":null,"type_of_any":1},"type_guard":null,"type_is":null,"unpack_kwargs":false,"variables":[]}}}},"abc":{".class":"SymbolTableNode","cross_ref":"abc","kind":"Gdef"},"get_dispatch_key":{".class":"SymbolTableNode","kind":"Gdef","node":{".class":"FuncDef","abstract_status":0,"arg_kinds":[0,1],"arg_names":["cls_or_instance","allow_missing"],"dataclass_transform_spec":null,"deprecated":null,"flags":[],"fullname":"prefect.utilities.dispatch.get_dispatch_key","name":"get_dispatch_key","type":{".class":"CallableType","arg_kinds":[0,1],"arg_names":["cls_or_instance","allow_missing"],"arg_types":[{".class":"AnyType","missing_import_name":null,"source_any":null,"type_of_any":2},"builtins.bool"],"bound_args":[],"def_extras":{"first_arg":null},"fallback":"builtins.function","from_concatenate":false,"implicit":false,"imprecise_arg_kinds":false,"is_ellipsis_args":false,"name":"get_dispatch_key","ret_type":{".class":"UnionType","items":["builtins.str",{".class":"NoneType"}],"uses_pep604_syntax":false},"type_guard":null,"type_is":null,"unpack_kwargs":false,"variables":[]}}},"get_registry_for_type":{".class":"SymbolTableNode","kind":"Gdef","node":{".class":"FuncDef","abstract_status":0,"arg_kinds":[0],"arg_names":["cls"],"dataclass_transform_spec":null,"deprecated":null,"flags":[],"fullname":"prefect.utilities.dispatch.get_registry_for_type","name":"get_registry_for_type","type":{".class":"CallableType","arg_kinds":[0],"arg_names":["cls"],"arg_types":[{".class":"TypeVarType","default":{".class":"AnyType","missing_import_name":null,"source_any":null,"type_of_any":4},"fullname":"prefect.utilities.dispatch.T","id":-1,"name":"T","namespace":"prefect.utilities.dispatch.get_registry_for_type","upper_bound":{".class":"TypeType","item":{".class":"AnyType","missing_import_name":null,"source_any":null,"type_of_any":4}},"values":[],"variance":0}],"bound_args":[],"def_extras":{"first_arg":null},"fallback":"builtins.function","from_concatenate":false,"implicit":false,"imprecise_arg_kinds":false,"is_ellipsis_args":false,"name":"get_registry_for_type","ret_type":{".class":"UnionType","items":[{".class":"Instance","args":["builtins.str",{".class":"TypeVarType","default":{".class":"AnyType","missing_import_name":null,"source_any":null,"type_of_any":4},"fullname":"prefect.utilities.dispatch.T","id":-1,"name":"T","namespace":"prefect.utilities.dispatch.get_registry_for_type","upper_bound":{".class":"TypeType","item":{".class":"AnyType","missing_import_name":null,"source_any":null,"type_of_any":4}},"values":[],"variance":0}],"extra_attrs":null,"type_ref":"builtins.dict"},{".class":"NoneType"}],"uses_pep604_syntax":false},"type_guard":null,"type_is":null,"unpack_kwargs":false,"variables":[{".class":"TypeVarType","default":{".class":"AnyType","missing_import_name":null,"source_any":null,"type_of_any":4},"fullname":"prefect.utilities.dispatch.T","id":-1,"name":"T","namespace":"prefect.utilities.dispatch.get_registry_for_type","upper_bound":{".class":"TypeType","item":{".class":"AnyType","missing_import_name":null,"source_any":null,"type_of_any":4}},"values":[],"variance":0}]}}},"inspect":{".class":"SymbolTableNode","cross_ref":"inspect","kind":"Gdef"},"lookup_type":{".class":"SymbolTableNode","kind":"Gdef","node":{".class":"FuncDef","abstract_status":0,"arg_kinds":[0,0],"arg_names":["cls","dispatch_key"],"dataclass_transform_spec":null,"deprecated":null,"flags":[],"fullname":"prefect.utilities.dispatch.lookup_type","name":"lookup_type","type":{".class":"CallableType","arg_kinds":[0,0],"arg_names":["cls","dispatch_key"],"arg_types":[{".class":"TypeVarType","default":{".class":"AnyType","missing_import_name":null,"source_any":null,"type_of_any":4},"fullname":"prefect.utilities.dispatch.T","id":-1,"name":"T","namespace":"prefect.utilities.dispatch.lookup_type","upper_bound":{".class":"TypeType","item":{".class":"AnyType","missing_import_name":null,"source_any":null,"type_of_any":4}},"values":[],"variance":0},"builtins.str"],"bound_args":[],"def_extras":{"first_arg":null},"fallback":"builtins.function","from_concatenate":false,"implicit":false,"imprecise_arg_kinds":false,"is_ellipsis_args":false,"name":"lookup_type","ret_type":{".class":"TypeVarType","default":{".class":"AnyType","missing_import_name":null,"source_any":null,"type_of_any":4},"fullname":"prefect.utilities.dispatch.T","id":-1,"name":"T","namespace":"prefect.utilities.dispatch.lookup_type","upper_bound":{".class":"TypeType","item":{".class":"AnyType","missing_import_name":null,"source_any":null,"type_of_any":4}},"values":[],"variance":0},"type_guard":null,"type_is":null,"unpack_kwargs":false,"variables":[{".class":"TypeVarType","default":{".class":"AnyType","missing_import_name":null,"source_any":null,"type_of_any":4},"fullname":"prefect.utilities.dispatch.T","id":-1,"name":"T","namespace":"prefect.utilities.dispatch.lookup_type","upper_bound":{".class":"TypeType","item":{".class":"AnyType","missing_import_name":null,"source_any":null,"type_of_any":4}},"values":[],"variance":0}]}}},"register_base_type":{".class":"SymbolTableNode","kind":"Gdef","node":{".class":"FuncDef","abstract_status":0,"arg_kinds":[0],"arg_names":["cls"],"dataclass_transform_spec":null,"deprecated":null,"flags":[],"fullname":"prefect.utilities.dispatch.register_base_type","name":"register_base_type","type":{".class":"CallableType","arg_kinds":[0],"arg_names":["cls"],"arg_types":[{".class":"TypeVarType","default":{".class":"AnyType","missing_import_name":null,"source_any":null,"type_of_any":4},"fullname":"prefect.utilities.dispatch.T","id":-1,"name":"T","namespace":"prefect.utilities.dispatch.register_base_type","upper_bound":{".class":"TypeType","item":{".class":"AnyType","missing_import_name":null,"source_any":null,"type_of_any":4}},"values":[],"variance":0}],"bound_args":[],"def_extras":{"first_arg":null},"fallback":"builtins.function","from_concatenate":false,"implicit":false,"imprecise_arg_kinds":false,"is_ellipsis_args":false,"name":"register_base_type","ret_type":{".class":"TypeVarType","default":{".class":"AnyType","missing_import_name":null,"source_any":null,"type_of_any":4},"fullname":"prefect.utilities.dispatch.T","id":-1,"name":"T","namespace":"prefect.utilities.dispatch.register_base_type","upper_bound":{".class":"TypeType","item":{".class":"AnyType","missing_import_name":null,"source_any":null,"type_of_any":4}},"values":[],"variance":0},"type_guard":null,"type_is":null,"unpack_kwargs":false,"variables":[{".class":"TypeVarType","default":{".class":"AnyType","missing_import_name":null,"source_any":null,"type_of_any":4},"fullname":"prefect.utilities.dispatch.T","id":-1,"name":"T","namespace":"prefect.utilities.dispatch.register_base_type","upper_bound":{".class":"TypeType","item":{".class":"AnyType","missing_import_name":null,"source_any":null,"type_of_any":4}},"values":[],"variance":0}]}}},"register_type":{".class":"SymbolTableNode","kind":"Gdef","node":{".class":"FuncDef","abstract_status":0,"arg_kinds":[0],"arg_names":["cls"],"dataclass_transform_spec":null,"deprecated":null,"flags":[],"fullname":"prefect.utilities.dispatch.register_type","name":"register_type","type":{".class":"CallableType","arg_kinds":[0],"arg_names":["cls"],"arg_types":[{".class":"TypeVarType","default":{".class":"AnyType","missing_import_name":null,"source_any":null,"type_of_any":4},"fullname":"prefect.utilities.dispatch.T","id":-1,"name":"T","namespace":"prefect.utilities.dispatch.register_type","upper_bound":{".class":"TypeType","item":{".class":"AnyType","missing_import_name":null,"source_any":null,"type_of_any":4}},"values":[],"variance":0}],"bound_args":[],"def_extras":{"first_arg":null},"fallback":"builtins.function","from_concatenate":false,"implicit":false,"imprecise_arg_kinds":false,"is_ellipsis_args":false,"name":"register_type","ret_type":{".class":"TypeVarType","default":{".class":"AnyType","missing_import_name":null,"source_any":null,"type_of_any":4},"fullname":"prefect.utilities.dispatch.T","id":-1,"name":"T","namespace":"prefect.utilities.dispatch.register_type","upper_bound":{".class":"TypeType","item":{".class":"AnyType","missing_import_name":null,"source_any":null,"type_of_any":4}},"values":[],"variance":0},"type_guard":null,"type_is":null,"unpack_kwargs":false,"variables":[{".class":"TypeVarType","default":{".class":"AnyType","missing_import_name":null,"source_any":null,"type_of_any":4},"fullname":"prefect.utilities.dispatch.T","id":-1,"name":"T","namespace":"prefect.utilities.dispatch.register_type","upper_bound":{".class":"TypeType","item":{".class":"AnyType","missing_import_name":null,"source_any":null,"type_of_any":4}},"values":[],"variance":0}]}}},"warnings":{".class":"SymbolTableNode","cross_ref":"warnings","kind":"Gdef"}},"path":"/Users/sveinugu/PycharmProjects/omnipy/.venv/lib/python3.10/site-packages/prefect/utilities/dispatch.py"}