{
    "uid": "DU5A",
    "label": "A13B4_mC102_8_17a11b_8a2b-001",
    "alias": [
        "A13B4_mC102_8_17a11b_8a2b"
    ],
    "title": "Monoclinic Co$_{4}$Al$_{13}$ Structure",
    "icsd": "57599",
    "ccdc": null,
    "prototype": "Al13Co4",
    "prototype_tex": "Al$_{13}$Co$_{4}$",
    "number_of_species": 2,
    "pearson_symbol": "mC102",
    "space_group_number": 8,
    "strukturbericht": null,
    "strukturbericht_tex": null,
    "part": 3,
    "parameter_symbols": [
        "a",
        "b/a",
        "c/a",
        "beta",
        "x1",
        "z1",
        "x2",
        "z2",
        "x3",
        "z3",
        "x4",
        "z4",
        "x5",
        "z5",
        "x6",
        "z6",
        "x7",
        "z7",
        "x8",
        "z8",
        "x9",
        "z9",
        "x10",
        "z10",
        "x11",
        "z11",
        "x12",
        "z12",
        "x13",
        "z13",
        "x14",
        "z14",
        "x15",
        "z15",
        "x16",
        "z16",
        "x17",
        "z17",
        "x18",
        "z18",
        "x19",
        "z19",
        "x20",
        "z20",
        "x21",
        "z21",
        "x22",
        "z22",
        "x23",
        "z23",
        "x24",
        "z24",
        "x25",
        "z25",
        "x26",
        "y26",
        "z26",
        "x27",
        "y27",
        "z27",
        "x28",
        "y28",
        "z28",
        "x29",
        "y29",
        "z29",
        "x30",
        "y30",
        "z30",
        "x31",
        "y31",
        "z31",
        "x32",
        "y32",
        "z32",
        "x33",
        "y33",
        "z33",
        "x34",
        "y34",
        "z34",
        "x35",
        "y35",
        "z35",
        "x36",
        "y36",
        "z36",
        "x37",
        "y37",
        "z37",
        "x38",
        "y38",
        "z38"
    ],
    "parameter_values": [
        15.183,
        0.53494,
        0.812751,
        107.9,
        0.671,
        0.72,
        0.077,
        0.576,
        0.755,
        0.034,
        0.095,
        0.788,
        0.246,
        0.969,
        0.923,
        0.424,
        0.905,
        0.212,
        0.945,
        0.826,
        0.703,
        0.231,
        0.768,
        0.468,
        0.233,
        0.531,
        0.478,
        0.831,
        0.498,
        0.501,
        0.298,
        0.77,
        0.055,
        0.175,
        0.33,
        0.28,
        0.523,
        0.169,
        0.396,
        0.627,
        0.914,
        0.618,
        0.091,
        0.988,
        0.403,
        0.982,
        0.087,
        0.383,
        0.605,
        0.374,
        0.91,
        0.013,
        0.598,
        0.018,
        0.678,
        0.28,
        0.334,
        0.869,
        0.289,
        0.468,
        0.992,
        0.279,
        0.331,
        0.876,
        0.271,
        0.112,
        0.686,
        0.282,
        0.112,
        0.502,
        0.248,
        0.0,
        0.633,
        0.21,
        0.523,
        0.509,
        0.224,
        0.669,
        0.824,
        0.219,
        0.666,
        0.636,
        0.21,
        0.889,
        0.815,
        0.217,
        0.889,
        0.682,
        0.292,
        0.723,
        0.818,
        0.229,
        0.278
    ],
    "compounds": {},
    "legacy": false,
    "notes": "Monoclinic",
    "comments": "Following (Hudd, 1962), the Al-IV and Al-XIII sites are occupied 30\\% of the time, while the occupation of Al-VI, Al-IX, Al-XIV, and Al-XVII is 70\\%.  This gives a nominal occupation of Al$_{91}$Co$_{30}$, though the authors state the actual composition is Al$_{68.3}$Co$_{24.4}$. \n Space group $Cm$ \\#8 allows an arbitrary choice for the origin of the $z$-axis.  We follow (Hudd, 1962) and set $z_{26} = 0$. \n If we allow the rather large uncertainty of 0.3{\\AA} in the atomic positions, FINDSYM sets the symmetry as $C2/m$ \\#12.  That crystal has the \\href{current_web_home_dir/A13B4_mC102_12_ah8i5j_4ij-001}{Al$_{13}$Fe$_{4}$} prototype. \n Co$_{4}$ has also been observed in a \\href{current_web_home_dir/A13B4_oP102_31_17a11b_8a2b-001}{orthorhombic structure}."
}