{
    "uid": "AT7V",
    "label": "A8B2C13_aP23_2_4i_i_a6i-001",
    "alias": null,
    "title": "$\\alpha$-K$_{2}$Bi$_{8}$Se$_{13}$ Structure",
    "icsd": "72976",
    "ccdc": null,
    "prototype": "Bi8K2Se13",
    "prototype_tex": "Bi$_{8}$K$_{2}$Se$_{13}$",
    "number_of_species": 3,
    "pearson_symbol": "aP23",
    "space_group_number": 2,
    "strukturbericht": null,
    "strukturbericht_tex": null,
    "part": 5,
    "parameter_symbols": [
        "a",
        "b/a",
        "c/a",
        "alpha",
        "beta",
        "gamma",
        "x2",
        "y2",
        "z2",
        "x3",
        "y3",
        "z3",
        "x4",
        "y4",
        "z4",
        "x5",
        "y5",
        "z5",
        "x6",
        "y6",
        "z6",
        "x7",
        "y7",
        "z7",
        "x8",
        "y8",
        "z8",
        "x9",
        "y9",
        "z9",
        "x10",
        "y10",
        "z10",
        "x11",
        "y11",
        "z11",
        "x12",
        "y12",
        "z12"
    ],
    "parameter_values": [
        13.768,
        0.878559,
        0.302557,
        89.98,
        98.64,
        87.96,
        0.8809,
        0.8803,
        0.4408,
        0.3787,
        0.0464,
        0.1887,
        0.151,
        0.794,
        0.0758,
        0.5628,
        0.3671,
        0.2822,
        0.831,
        0.551,
        0.415,
        0.2625,
        0.9267,
        0.632,
        0.037,
        0.6977,
        0.516,
        0.7788,
        0.7707,
        0.887,
        0.5094,
        0.8536,
        0.254,
        0.2811,
        0.6169,
        0.14,
        0.5837,
        0.5886,
        0.293
    ],
    "compounds": {},
    "legacy": false,
    "notes": null,
    "comments": "We have shifted the Se I atom from the (1c) site to the origin at the (1a) site. \n K$_{2}$Bi$_{8}$Se$_{13}$ can also be found in the \\href{current_web_home_dir/A8B2C13_mP46_11_8e_2e_13e-001}{monoclinic $\\beta$ phase}."
}