{".class":"MypyFile","_fullname":"prefect.server.events.stream","future_import_flags":[],"is_partial_stub_package":false,"is_stub":false,"names":{".class":"SymbolTable","AsyncGenerator":{".class":"SymbolTableNode","cross_ref":"typing.AsyncGenerator","kind":"Gdef"},"AsyncIterable":{".class":"SymbolTableNode","cross_ref":"typing.AsyncIterable","kind":"Gdef"},"Dict":{".class":"SymbolTableNode","cross_ref":"typing.Dict","kind":"Gdef"},"Distributor":{".class":"SymbolTableNode","kind":"Gdef","node":{".class":"TypeInfo","_promote":[],"abstract_attributes":[],"alt_promote":null,"bases":["builtins.object"],"dataclass_transform_spec":null,"declared_metaclass":null,"defn":{".class":"ClassDef","fullname":"prefect.server.events.stream.Distributor","name":"Distributor","type_vars":[]},"deletable_attributes":[],"deprecated":null,"flags":[],"fullname":"prefect.server.events.stream.Distributor","has_param_spec_type":false,"metaclass_type":null,"metadata":{},"module_name":"prefect.server.events.stream","mro":["prefect.server.events.stream.Distributor","builtins.object"],"names":{".class":"SymbolTable","name":{".class":"SymbolTableNode","kind":"Mdef","node":{".class":"Var","flags":["is_initialized_in_class","is_ready","has_explicit_value"],"fullname":"prefect.server.events.stream.Distributor.name","name":"name","type":"builtins.str"}},"start":{".class":"SymbolTableNode","kind":"Mdef","node":{".class":"FuncDef","abstract_status":0,"arg_kinds":[0],"arg_names":["self"],"dataclass_transform_spec":null,"deprecated":null,"flags":["is_coroutine"],"fullname":"prefect.server.events.stream.Distributor.start","name":"start","type":null}},"stop":{".class":"SymbolTableNode","kind":"Mdef","node":{".class":"FuncDef","abstract_status":0,"arg_kinds":[0],"arg_names":["self"],"dataclass_transform_spec":null,"deprecated":null,"flags":["is_coroutine"],"fullname":"prefect.server.events.stream.Distributor.stop","name":"stop","type":null}}},"self_type":{".class":"TypeVarType","default":{".class":"AnyType","missing_import_name":null,"source_any":null,"type_of_any":4},"fullname":"prefect.server.events.stream.Distributor.Self","id":0,"name":"Self","namespace":"","upper_bound":"prefect.server.events.stream.Distributor","values":[],"variance":0},"slots":null,"tuple_type":null,"type_vars":[],"typeddict_type":null}},"EventFilter":{".class":"SymbolTableNode","cross_ref":"prefect.server.events.filters.EventFilter","kind":"Gdef"},"Queue":{".class":"SymbolTableNode","cross_ref":"asyncio.queues.Queue","kind":"Gdef"},"ReceivedEvent":{".class":"SymbolTableNode","cross_ref":"prefect.server.events.schemas.events.ReceivedEvent","kind":"Gdef"},"SUBSCRIPTION_BACKLOG":{".class":"SymbolTableNode","kind":"Gdef","node":{".class":"Var","flags":["is_ready","is_inferred","has_explicit_value"],"fullname":"prefect.server.events.stream.SUBSCRIPTION_BACKLOG","name":"SUBSCRIPTION_BACKLOG","type":"builtins.int"}},"Set":{".class":"SymbolTableNode","cross_ref":"typing.Set","kind":"Gdef"},"__annotations__":{".class":"SymbolTableNode","kind":"Gdef","node":{".class":"Var","flags":["is_ready"],"fullname":"prefect.server.events.stream.__annotations__","name":"__annotations__","type":{".class":"Instance","args":["builtins.str",{".class":"AnyType","missing_import_name":null,"source_any":null,"type_of_any":6}],"extra_attrs":null,"type_ref":"builtins.dict"}}},"__doc__":{".class":"SymbolTableNode","kind":"Gdef","node":{".class":"Var","flags":["is_ready"],"fullname":"prefect.server.events.stream.__doc__","name":"__doc__","type":"builtins.str"}},"__file__":{".class":"SymbolTableNode","kind":"Gdef","node":{".class":"Var","flags":["is_ready"],"fullname":"prefect.server.events.stream.__file__","name":"__file__","type":"builtins.str"}},"__name__":{".class":"SymbolTableNode","kind":"Gdef","node":{".class":"Var","flags":["is_ready"],"fullname":"prefect.server.events.stream.__name__","name":"__name__","type":"builtins.str"}},"__package__":{".class":"SymbolTableNode","kind":"Gdef","node":{".class":"Var","flags":["is_ready"],"fullname":"prefect.server.events.stream.__package__","name":"__package__","type":"builtins.str"}},"__spec__":{".class":"SymbolTableNode","kind":"Gdef","node":{".class":"Var","flags":["is_ready"],"fullname":"prefect.server.events.stream.__spec__","name":"__spec__","type":"_frozen_importlib.ModuleSpec"}},"_distributor_started":{".class":"SymbolTableNode","kind":"Gdef","node":{".class":"Var","flags":["is_ready","has_explicit_value"],"fullname":"prefect.server.events.stream._distributor_started","name":"_distributor_started","type":{".class":"UnionType","items":["asyncio.locks.Event",{".class":"NoneType"}],"uses_pep604_syntax":true}}},"_distributor_task":{".class":"SymbolTableNode","kind":"Gdef","node":{".class":"Var","flags":["is_ready","has_explicit_value"],"fullname":"prefect.server.events.stream._distributor_task","name":"_distributor_task","type":{".class":"UnionType","items":[{".class":"Instance","args":[{".class":"AnyType","missing_import_name":null,"source_any":null,"type_of_any":4}],"extra_attrs":null,"type_ref":"_asyncio.Task"},{".class":"NoneType"}],"uses_pep604_syntax":true}}},"asynccontextmanager":{".class":"SymbolTableNode","cross_ref":"contextlib.asynccontextmanager","kind":"Gdef"},"asyncio":{".class":"SymbolTableNode","cross_ref":"asyncio","kind":"Gdef"},"distributor":{".class":"SymbolTableNode","kind":"Gdef","node":{".class":"Decorator","func":{".class":"FuncDef","abstract_status":0,"arg_kinds":[],"arg_names":[],"dataclass_transform_spec":null,"deprecated":null,"flags":["is_generator","is_coroutine","is_async_generator","is_decorated"],"fullname":"prefect.server.events.stream.distributor","name":"distributor","type":{".class":"CallableType","arg_kinds":[],"arg_names":[],"arg_types":[],"bound_args":[],"def_extras":{"first_arg":null},"fallback":"builtins.function","from_concatenate":false,"implicit":false,"imprecise_arg_kinds":false,"is_ellipsis_args":false,"name":"distributor","ret_type":{".class":"Instance","args":[{".class":"TypeAliasType","args":[],"type_ref":"prefect.server.utilities.messaging.MessageHandler"},{".class":"NoneType"}],"extra_attrs":null,"type_ref":"typing.AsyncGenerator"},"type_guard":null,"type_is":null,"unpack_kwargs":false,"variables":[]}},"is_overload":false,"var":{".class":"Var","flags":["is_ready","is_inferred"],"fullname":"prefect.server.events.stream.distributor","name":"distributor","type":{".class":"CallableType","arg_kinds":[],"arg_names":[],"arg_types":[],"bound_args":[],"def_extras":{},"fallback":"builtins.function","from_concatenate":false,"implicit":false,"imprecise_arg_kinds":false,"is_ellipsis_args":false,"name":"distributor","ret_type":{".class":"Instance","args":[{".class":"CallableType","arg_kinds":[0],"arg_names":[null],"arg_types":["prefect.server.utilities.messaging.Message"],"bound_args":[],"def_extras":{},"fallback":"builtins.function","from_concatenate":false,"implicit":false,"imprecise_arg_kinds":false,"is_ellipsis_args":false,"name":null,"ret_type":{".class":"Instance","args":[{".class":"NoneType"}],"extra_attrs":null,"type_ref":"typing.Awaitable"},"type_guard":null,"type_is":null,"unpack_kwargs":false,"variables":[]},{".class":"NoneType"}],"extra_attrs":null,"type_ref":"contextlib._AsyncGeneratorContextManager"},"type_guard":null,"type_is":null,"unpack_kwargs":false,"variables":[]}}}},"events":{".class":"SymbolTableNode","kind":"Gdef","node":{".class":"Decorator","func":{".class":"FuncDef","abstract_status":0,"arg_kinds":[0],"arg_names":["filter"],"dataclass_transform_spec":null,"deprecated":null,"flags":["is_generator","is_coroutine","is_async_generator","is_decorated"],"fullname":"prefect.server.events.stream.events","name":"events","type":{".class":"CallableType","arg_kinds":[0],"arg_names":["filter"],"arg_types":["prefect.server.events.filters.EventFilter"],"bound_args":[],"def_extras":{"first_arg":null},"fallback":"builtins.function","from_concatenate":false,"implicit":false,"imprecise_arg_kinds":false,"is_ellipsis_args":false,"name":"events","ret_type":{".class":"Instance","args":[{".class":"Instance","args":["prefect.server.events.schemas.events.ReceivedEvent"],"extra_attrs":null,"type_ref":"typing.AsyncIterable"},{".class":"NoneType"}],"extra_attrs":null,"type_ref":"typing.AsyncGenerator"},"type_guard":null,"type_is":null,"unpack_kwargs":false,"variables":[]}},"is_overload":false,"var":{".class":"Var","flags":["is_ready","is_inferred"],"fullname":"prefect.server.events.stream.events","name":"events","type":{".class":"CallableType","arg_kinds":[0],"arg_names":["filter"],"arg_types":["prefect.server.events.filters.EventFilter"],"bound_args":[],"def_extras":{},"fallback":"builtins.function","from_concatenate":false,"implicit":false,"imprecise_arg_kinds":false,"is_ellipsis_args":false,"name":"events","ret_type":{".class":"Instance","args":[{".class":"Instance","args":["prefect.server.events.schemas.events.ReceivedEvent"],"extra_attrs":null,"type_ref":"typing.AsyncIterable"},{".class":"NoneType"}],"extra_attrs":null,"type_ref":"contextlib._AsyncGeneratorContextManager"},"type_guard":null,"type_is":null,"unpack_kwargs":false,"variables":[]}}}},"filters":{".class":"SymbolTableNode","kind":"Gdef","node":{".class":"Var","flags":["is_ready","has_explicit_value"],"fullname":"prefect.server.events.stream.filters","name":"filters","type":{".class":"Instance","args":[{".class":"Instance","args":["prefect.server.events.schemas.events.ReceivedEvent"],"extra_attrs":null,"type_ref":"asyncio.queues.Queue"},"prefect.server.events.filters.EventFilter"],"extra_attrs":null,"type_ref":"builtins.dict"}}},"get_logger":{".class":"SymbolTableNode","cross_ref":"prefect.logging.loggers.get_logger","kind":"Gdef"},"logger":{".class":"SymbolTableNode","kind":"Gdef","node":{".class":"Var","flags":["is_inferred","has_explicit_value"],"fullname":"prefect.server.events.stream.logger","name":"logger","type":"logging.Logger"}},"messaging":{".class":"SymbolTableNode","cross_ref":"prefect.server.utilities.messaging","kind":"Gdef"},"run_distributor":{".class":"SymbolTableNode","kind":"Gdef","node":{".class":"FuncDef","abstract_status":0,"arg_kinds":[0],"arg_names":["started"],"dataclass_transform_spec":null,"deprecated":null,"flags":["is_coroutine"],"fullname":"prefect.server.events.stream.run_distributor","name":"run_distributor","type":{".class":"CallableType","arg_kinds":[0],"arg_names":["started"],"arg_types":["asyncio.locks.Event"],"bound_args":[],"def_extras":{"first_arg":null},"fallback":"builtins.function","from_concatenate":false,"implicit":false,"imprecise_arg_kinds":false,"is_ellipsis_args":false,"name":"run_distributor","ret_type":{".class":"Instance","args":[{".class":"AnyType","missing_import_name":null,"source_any":null,"type_of_any":6},{".class":"AnyType","missing_import_name":null,"source_any":null,"type_of_any":6},{".class":"AnyType","missing_import_name":null,"source_any":null,"type_of_any":1}],"extra_attrs":null,"type_ref":"typing.Coroutine"},"type_guard":null,"type_is":null,"unpack_kwargs":false,"variables":[]}}},"start_distributor":{".class":"SymbolTableNode","kind":"Gdef","node":{".class":"FuncDef","abstract_status":0,"arg_kinds":[],"arg_names":[],"dataclass_transform_spec":null,"deprecated":null,"flags":["is_coroutine"],"fullname":"prefect.server.events.stream.start_distributor","name":"start_distributor","type":null}},"stop_distributor":{".class":"SymbolTableNode","kind":"Gdef","node":{".class":"FuncDef","abstract_status":0,"arg_kinds":[],"arg_names":[],"dataclass_transform_spec":null,"deprecated":null,"flags":["is_coroutine"],"fullname":"prefect.server.events.stream.stop_distributor","name":"stop_distributor","type":null}},"subscribed":{".class":"SymbolTableNode","kind":"Gdef","node":{".class":"Decorator","func":{".class":"FuncDef","abstract_status":0,"arg_kinds":[0],"arg_names":["filter"],"dataclass_transform_spec":null,"deprecated":null,"flags":["is_generator","is_coroutine","is_async_generator","is_decorated"],"fullname":"prefect.server.events.stream.subscribed","name":"subscribed","type":{".class":"CallableType","arg_kinds":[0],"arg_names":["filter"],"arg_types":["prefect.server.events.filters.EventFilter"],"bound_args":[],"def_extras":{"first_arg":null},"fallback":"builtins.function","from_concatenate":false,"implicit":false,"imprecise_arg_kinds":false,"is_ellipsis_args":false,"name":"subscribed","ret_type":{".class":"Instance","args":[{".class":"Instance","args":["prefect.server.events.schemas.events.ReceivedEvent"],"extra_attrs":null,"type_ref":"asyncio.queues.Queue"},{".class":"NoneType"}],"extra_attrs":null,"type_ref":"typing.AsyncGenerator"},"type_guard":null,"type_is":null,"unpack_kwargs":false,"variables":[]}},"is_overload":false,"var":{".class":"Var","flags":["is_ready","is_inferred"],"fullname":"prefect.server.events.stream.subscribed","name":"subscribed","type":{".class":"CallableType","arg_kinds":[0],"arg_names":["filter"],"arg_types":["prefect.server.events.filters.EventFilter"],"bound_args":[],"def_extras":{},"fallback":"builtins.function","from_concatenate":false,"implicit":false,"imprecise_arg_kinds":false,"is_ellipsis_args":false,"name":"subscribed","ret_type":{".class":"Instance","args":[{".class":"Instance","args":["prefect.server.events.schemas.events.ReceivedEvent"],"extra_attrs":null,"type_ref":"asyncio.queues.Queue"},{".class":"NoneType"}],"extra_attrs":null,"type_ref":"contextlib._AsyncGeneratorContextManager"},"type_guard":null,"type_is":null,"unpack_kwargs":false,"variables":[]}}}},"subscribers":{".class":"SymbolTableNode","kind":"Gdef","node":{".class":"Var","flags":["is_ready","has_explicit_value"],"fullname":"prefect.server.events.stream.subscribers","name":"subscribers","type":{".class":"Instance","args":[{".class":"Instance","args":["prefect.server.events.schemas.events.ReceivedEvent"],"extra_attrs":null,"type_ref":"asyncio.queues.Queue"}],"extra_attrs":null,"type_ref":"builtins.set"}}}},"path":"/Users/sveinugu/PycharmProjects/omnipy/.venv/lib/python3.10/site-packages/prefect/server/events/stream.py"}