{
    "uid": "5BWB",
    "label": "ABC4_mP12_13_e_a_2g-001",
    "alias": [
        "ABC4_mP12_13_e_a_2g"
    ],
    "title": "Sylvanite (AgAuTe$_{4}$, $E1_{b}$) Structure",
    "icsd": "30874",
    "ccdc": null,
    "prototype": "AgAuTe4",
    "prototype_tex": "AgAuTe$_{4}$",
    "number_of_species": 3,
    "pearson_symbol": "mP12",
    "space_group_number": 13,
    "strukturbericht": "E1_b",
    "strukturbericht_tex": "$E1_{b}$",
    "part": 1,
    "parameter_symbols": [
        "a",
        "b/a",
        "c/a",
        "beta",
        "y2",
        "x3",
        "y3",
        "z3",
        "x4",
        "y4",
        "z4"
    ],
    "parameter_values": [
        8.95,
        0.500335,
        1.63361,
        145.35,
        0.5182,
        0.2986,
        0.0278,
        0.0003,
        0.2821,
        0.4045,
        0.2366
    ],
    "compounds": {},
    "legacy": false,
    "notes": "$E1_{b}$, Sylvanite",
    "comments": null
}