{
    "uid": "6XPU",
    "label": "AB2_oC6_21_a_k-001",
    "alias": [
        "AB2_oC6_21_a_k"
    ],
    "title": "Ta$_{2}$H Structure",
    "icsd": "41774",
    "ccdc": null,
    "prototype": "HTa2",
    "prototype_tex": "HTa$_{2}$",
    "number_of_species": 2,
    "pearson_symbol": "oC6",
    "space_group_number": 21,
    "strukturbericht": null,
    "strukturbericht_tex": null,
    "part": 2,
    "parameter_symbols": [
        "a",
        "b/a",
        "c/a",
        "z2"
    ],
    "parameter_values": [
        3.398,
        1.39432,
        1.40165,
        0.262
    ],
    "compounds": {},
    "legacy": false,
    "notes": null,
    "comments": "Th$_{2}$H and \\href{current_web_home_dir/AB2_oC6_21_a_k-002}{HoSb$_{2}$} share the same AFLOW prototype label, AB2\\_oC6\\_21\\_a\\_k. The structures are generated by the same symmetry operations with different sets of parameters ({\\tt --params}) specified in their corresponding CIF files."
}