{
    "uid": "2EBJ",
    "label": "A2B4C8D_oC30_65_h_2g_3gh_c-001",
    "alias": null,
    "title": "``124 Superconductor'' (YBa$_{2}$Cu$_{4}$O$_{8}$) Structure",
    "icsd": null,
    "ccdc": null,
    "prototype": "Ba2Cu4O8Y",
    "prototype_tex": "Ba$_{2}$Cu$_{4}$O$_{8}$Y",
    "number_of_species": 4,
    "pearson_symbol": "oC30",
    "space_group_number": 65,
    "strukturbericht": null,
    "strukturbericht_tex": null,
    "part": 4,
    "parameter_symbols": [
        "a",
        "b/a",
        "c/a",
        "x2",
        "x3",
        "x4",
        "x5",
        "x6",
        "x7",
        "x8"
    ],
    "parameter_values": [
        27.263,
        0.142171,
        0.141048,
        0.21298,
        0.06153,
        0.14545,
        0.55236,
        0.71801,
        0.63483,
        0.05228
    ],
    "compounds": {},
    "legacy": false,
    "notes": "``124 Superconductor''",
    "comments": "Unlike most BCO-type superconductors, the stoichiometry of YBa$_{2}$Cu$_{4}$O$_{8}$ is fixed. \n We use the ambient pressure data from (Bordet, 1989) taken at room temperature.  \n Although it is never explicitly stated by (Bordet, 1989), (Nelmes, 1990) notes that this data is given in the $Ammm$ setting of space group \\#65, making the long axis in the $z$-direction.  The standard orientation is $Cmmm$, and we use FINDSYM to rotate the structure, putting the long axis in the $x$-direction."
}